cql3dui/.cql3d_gui_config.json
cql3dui/__init__.py
cql3dui/cqlgui.py
cql3dui/cqlyaml.yaml
cql3dui/cql3dtests/aux_file_folder/eqdsk
cql3dui/cql3dtests/aux_file_folder/eqdsk_MAST-like
cql3dui/cql3dtests/aux_file_folder/eqdsk_freidberg_full_eps
cql3dui/cql3dtests/aux_file_folder/fpld_dsk
cql3dui/cql3dtests/aux_file_folder/g096143.01440
cql3dui/cql3dtests/aux_file_folder/g122080.03100
cql3dui/cql3dtests/aux_file_folder/genray_test4.nc
cql3dui/cql3dtests/aux_file_folder/genrayfw_18rays.nc
cql3dui/cql3dtests/aux_file_folder/rayech
cql3dui/cql3dtests/cqlinput_tests/test1_cqlinput_eoved_.16_multi-flux-surface_test1.0
cql3dui/cql3dtests/cqlinput_tests/test1_cqlinput_eoved_.16_multi-flux-surface_test1.1
cql3dui/cql3dtests/cqlinput_tests/test2_cqlinput_freidberg_full_eps.3_short_w_sxr_201024
cql3dui/cql3dtests/cqlinput_tests/test3_cqlinput_96143_one_ray.1_short_201024
cql3dui/cql3dtests/cqlinput_tests/test4_cqlinput_MAST-like_test.0
cql3dui/cql3dtests/cqlinput_tests/test5_cqlinput_H0.short_mmsv8_adjust.4
cql3dui/cql3dtests/cqlinput_tests/test6_cqlinput_eoved_.16_multi-flux-surface0.2.11
cql3dui/cql3dtests/cqlinput_tests/test7_cqlinput_cmod1101201020_AF.26
cql3dui/sginfo/_general.txt
cql3dui/sginfo/amperefaradaymodule.txt
cql3dui/sginfo/analyticsourcecontrol.txt
cql3dui/sginfo/basicsetup.txt
cql3dui/sginfo/bootstrapcurrent.txt
cql3dui/sginfo/collisionalinput.txt
cql3dui/sginfo/cqlpmodule.txt
cql3dui/sginfo/currentdrivediagnostics.txt
cql3dui/sginfo/dcelectricfield.txt
cql3dui/sginfo/differencingandsolutionmethod.txt
cql3dui/sginfo/energyandparticlelosses.txt
cql3dui/sginfo/equilibriumcontrols.txt
cql3dui/sginfo/firstorbitshift.txt
cql3dui/sginfo/freyamodule.txt
cql3dui/sginfo/fusionreactions.txt
cql3dui/sginfo/knockonsourcecontrol.txt
cql3dui/sginfo/machinegeometry.txt
cql3dui/sginfo/meshcontrols.txt
cql3dui/sginfo/npadiagnostic.txt
cql3dui/sginfo/partnercodes.txt
cql3dui/sginfo/plotandoutputcontrols.txt
cql3dui/sginfo/rdcmodule.txt
cql3dui/sginfo/softxraydiagnostics.txt
cql3dui-0.0.10.dist-info/METADATA
cql3dui-0.0.10.dist-info/WHEEL
cql3dui-0.0.10.dist-info/entry_points.txt
cql3dui-0.0.10.dist-info/top_level.txt
cql3dui-0.0.10.dist-info/RECORD
