Metadata-Version: 2.4
Name: CQL3DUI
Version: 0.0.10
Summary: A small UI for running CQL3D
Author-email: Matthew Poulos <poulos@compxco.com>
Project-URL: Homepage, https://github.com/username/my_package
Requires-Python: >=3.7
Requires-Dist: numpy
Requires-Dist: matplotlib
Requires-Dist: netCDF4
Requires-Dist: PyYAML
Requires-Dist: f90nml
Requires-Dist: ttkbootstrap
Requires-Dist: darkdetect
